maldet/__init__.py
maldet/cli.py
maldet/config.py
maldet/constants.py
maldet/detector.py
maldet/exceptions.py
maldet/logging.py
islab_malware_detector-0.4.0.dist-info/METADATA
islab_malware_detector-0.4.0.dist-info/WHEEL
islab_malware_detector-0.4.0.dist-info/licenses/LICENCE.txt
islab_malware_detector-0.4.0.dist-info/RECORD
