Metadata-Version: 2.4
Name: islab-malware-detector
Version: 0.4.0
Summary: Base framework for building malware detectors
Project-URL: Homepage, https://github.com/bolin8017/islab-malware-detector
Project-URL: Documentation, https://github.com/bolin8017/islab-malware-detector/wiki
Project-URL: Repository, https://github.com/bolin8017/islab-malware-detector.git
Author-email: PO-LIN LAI <bolin8017@gmail.com>
License: MIT
License-File: LICENCE.txt
Keywords: detector,framework,malware,security
Classifier: Development Status :: 4 - Beta
Classifier: Intended Audience :: Developers
Classifier: License :: OSI Approved :: MIT License
Classifier: Programming Language :: Python :: 3.12
Classifier: Programming Language :: Python :: 3.13
Classifier: Typing :: Typed
Requires-Python: >=3.12
Requires-Dist: pydantic-settings<3.0,>=2.0
Requires-Dist: pydantic<3.0,>=2.0
Requires-Dist: structlog<25.0,>=24.0
Requires-Dist: typer<1.0,>=0.9
Provides-Extra: dev
Requires-Dist: mypy<2.0,>=1.8; extra == 'dev'
Requires-Dist: pytest-cov<5.0,>=4.0; extra == 'dev'
Requires-Dist: pytest<9.0,>=8.0; extra == 'dev'
Requires-Dist: ruff<1.0,>=0.1; extra == 'dev'
